ALU.v
module alu(arg1,arg2,func_code,out,zero,shamt,clk);
input wire[31:0] arg1,arg2;
input wire[2:0] func_code;
output reg[31:0] out;
output reg zero;
input clk;
input wire[4:0] shamt;
reg jump;
always@(posedge clk) begin
case(func_code)
  0: begin
  out <= arg1 + arg2;
  zero <= 0;   //add,addi,addu,addiu, lw, sw
  end
  1: begin
  out <= arg1 - arg2;  //sub,subu
  zero<= 0;
  end
  2: begin
  out <= arg1 & arg2;  //and,andi
  zero<=0;
  end
  3: begin
  out <= arg1 || arg2;  //or,ori
  zero<=0;
  end
  4: begin
  out <= (arg1<<shamt); //sll
  zero<=0;
  end
  5: begin
  out <= (arg1>>shamt); //srl
  zero<= 0;
  end
  6: begin             //slt,slti
    if(arg1<arg2)begin
    out<=1;
    zero<=0;
    end
    else begin
    out<=0;
    zero<=0;
    end
  end
  7: begin
    zero<=1;
  end
  8: begin
    zero<=1;
  end


  endcase
end
endmodule

opcode.v


module op_decode(
    input wire[31:0] ins,
    
    output reg[2:0] data_path,
    output reg[2:0] type,
    input clk
);





always@(posedge clk)begin
  
  if(ins[31:26]<6'd3)begin
    data_path<=1;  //arithmetic
    if(ins[5:0]==34 || ins[5:0]==35)begin
    type<= 1; //sub,subu
    end
    else begin
    type<= 0; //addi,add,addu,addiu
    end
  end
  else if(ins[31:26]<6'd16 && ins[31:26]>=6'd8)begin
    data_path<=2;  //logical
    if(ins[5:0]==36 || ins[31:26]==13)begin
    type<= 2;
    end
    else if(ins[31:26]==15)begin
    type<= 4;
    end
    else if(ins[31:26]==10)begin
    type<=5;
    end
    else begin
    type<=3;
    end

  end
  else if(ins[31:26]==6'd40 || ins[31:26]==6'd41)begin
    data_path<=3;   //meomory
  end
  else if(ins[31:26]==6'd32 || ins[31:26]==6'd33)begin
    data_path<=4;    //comparator
    type<=6;
  end
  else if(ins[31:26]>6'd50)begin
    data_path<=5;    //jump
  end
  else begin
    data_path<=6;    //branching
    if(ins[31:26]==20) begin
      type<= 7;   //beq

    end
    else if(ins[31:26]==21)begin
      type<=8;  //bne
    end
    else if(ins[31:26]==23)begin
      type<=9; //bgt
    end
  end




end




endmodule

ins_fetch.v
module instruction_fetch(input wire [15:0] mem_addr, output reg[31:0] ins, input clk );
reg [31:0]ins_address[31:0];


initial begin
  ins_address[0] = {6'b000000,5'b00001,5'b00010,5'b00000,5'b00000,6'b100000};  //add
  ins_address[1] = {6'b000000,5'b00001,5'b00010,5'b00000,5'b00000,6'b100010};  //sub
  ins_address[2] = {6'b000000,5'b00001,5'b00010,5'b00000,5'b00000,6'b100001}; //addu
  ins_address[3] = {6'b000000,5'b00001,5'b00010,5'b00000,5'b00000,6'b100011}; //subu
  ins_address[4] = {6'b000010,5'b00001,5'b00000,16'd1000}; //addi
  ins_address[5] = {6'b000001,5'b00001,5'b00000,16'd1000}; //addiu
  ins_address[6] = {6'b001100,5'b00001,5'b00010,5'b00000,5'b00000,6'b100100}; //and
  ins_address[7] = {6'b001100,5'b00001,5'b00010,5'b00000,5'b00000,6'b100101}; //or
  ins_address[8] = {6'b001101,5'b00001,5'b00000,16'd1000};//andi
  ins_address[9] = {6'b001011,5'b00001,5'b00000,16'd1000};//ori
  ins_address[10] = {6'b001111,5'b00001,5'b00010,5'b00000,5'd10,6'b000000};  //sll
  ins_address[11] = {6'b001010,5'b00001,5'b00000,5'b00000,5'd10,6'b000010};  //srl
  ins_address[12] = {6'b100001,5'b00001,5'b00000,16'd10};  //lw
  ins_address[13] = {6'b100000,5'b00001,5'b00000,16'd10}; //sw
  ins_address[14] = {6'b010100,5'b00001,5'b00000,16'd10};  //beq
  ins_address[15] = {6'b010101,5'b00001,5'b00000,16'd10}; //bne
  ins_address[16] = {6'b010111,5'b00001,5'b00000,16'd10}; //bgt
  ins_address[17] = {6'b010001,5'b00001,5'b00000,16'd10}; //bgte
  ins_address[18] = {6'b010011,5'b00001,5'b00000,16'd10}; //ble
  ins_address[19] = {6'b010101,5'b00001,5'b00000,16'd10}; //bleq
  ins_address[20] = {6'b111101,26'd10}; //j
  ins_address[21] =  {6'b111111,5'b00000,5'b00000,5'b00000,5'b00000,6'b001000};//jr
  ins_address[22] =  {6'b111110,5'b00000,5'b00000,5'b00000,5'b00000,6'b001001};//jal
  ins_address[23] =  {6'b101000,5'b00001,5'b00010,5'b00000,5'b00000,6'b101010};//slt
  ins_address[24] =  {6'b101001,5'b00001,5'b00000,16'd100};//slti

  



end
always@(posedge clk)begin
ins = ins_address[mem_addr];
end

endmodule

cpu.v
`include "ins_fetch.v"
`include "opcode.v"
`include "ALU.v"


module cpu(pc,clk,pc_out,rs,rt,rd);
input [15:0] pc;
input clk;
wire[31:0] ins;
output reg[15:0] pc_out;
output reg[31:0] rs,rt;
output wire[31:0] rd;
wire[2:0] data_pth;
wire[2:0] type;
wire zero;
reg[31:0] data_memory[31:0];
reg[4:0] shamt;
reg[15:0] offset;
integer  i;
reg jump;
    initial begin
    for(i=0;i<32;i=i+1)begin
      data_memory[i]<=1;
    end
    end
    
   instruction_fetch inf(pc,ins,clk);

   op_decode op(ins,data_pth,type,clk);
   always@(posedge clk) begin
    if(ins[31:26]==0 || ins[31:26]==12)begin
    
    rs<=data_memory[ins[25:21]][31:0];
    rt<=data_memory[ins[20:16]][31:0];
    jump<=0;
    

    end
    else if(ins[31:26]<=2)begin
    
    rs<=data_memory[ins[25:21]][31:0];
    jump<=0;
    rt<={16'd0,ins[15:0]};
    end
    else if(ins[31:26]==15)begin
       rs<=data_memory[ins[25:21]][31:0];
    
       jump<=0;

    shamt<= ins[10:6];
    end
    else if(ins[31:26]==10)begin
       rs<=data_memory[ins[25:21]][31:0];
       jump<=0;
    

    shamt<= ins[10:6];
    end
    else if(type==7)begin
      rs<=data_memory[ins[25:21]][31:0];
      rt<=data_memory[ins[20:16]][31:0];
      if(rs==rt)begin
         jump<=1;
      end
      
    end
    else if(type==8)begin
      rs<=data_memory[ins[25:21]][31:0];
      rt<=data_memory[ins[20:16]][31:0];
      if(rs!=rt)begin
         jump<=1;
    end


   end
end
   alu al(rs,rt,type,rd,zero,shamt,clk);

   always@(posedge clk)begin
      if(type!=7)begin
     data_memory[ins[15:10]][31:0]<=rd;
      end
      else begin
         if(jump==1 && zero==1)begin
            offset<= (ins[15:0]<<2);
            pc_out = pc + offset;
         end
      end
   end


endmodule

test_deco.v
`include "cpu.v"
`timescale 1ns/1ns
module testbench;
  
  reg[15:0] pc;
  wire[15:0] pc_out;
  reg clk;
  wire[31:0] rs,rt,rd;
  cpu cp(pc,clk,pc_out,rs,rt,rd);
  initial begin
   clk = 0;
  end
  always begin
    #5 clk=~clk;
  end
  initial begin
    $dumpfile("dmp.vcd");
    $dumpvars(0,testbench);
  pc = 0; //add
  #40;
  pc=1; //sub
  #20;
  pc=6; //and
  #20;
  pc=10; //sll
  #20;
  pc=14; //beq

   
   #80;
    $finish;
    
  
  end
  

  
  
  
  
  

endmodule

dmp.vcd
$date
	Wed Mar 29 15:04:27 2023
$end
$version
	Icarus Verilog
$end
$timescale
	1ns
$end
$scope module testbench $end
$var wire 32 ! rt [31:0] $end
$var wire 32 " rs [31:0] $end
$var wire 32 # rd [31:0] $end
$var wire 16 $ pc_out [15:0] $end
$var reg 1 % clk $end
$var reg 16 & pc [15:0] $end
$scope module cp $end
$var wire 1 % clk $end
$var wire 16 ' pc [15:0] $end
$var wire 1 ( zero $end
$var wire 3 ) type [2:0] $end
$var wire 32 * rd [31:0] $end
$var wire 32 + ins [31:0] $end
$var wire 3 , data_pth [2:0] $end
$var reg 1 - jump $end
$var reg 16 . offset [15:0] $end
$var reg 16 / pc_out [15:0] $end
$var reg 32 0 rs [31:0] $end
$var reg 32 1 rt [31:0] $end
$var reg 5 2 shamt [4:0] $end
$var integer 32 3 i [31:0] $end
$scope module al $end
$var wire 32 4 arg1 [31:0] $end
$var wire 32 5 arg2 [31:0] $end
$var wire 1 % clk $end
$var wire 5 6 shamt [4:0] $end
$var wire 3 7 func_code [2:0] $end
$var reg 32 8 out [31:0] $end
$var reg 1 ( zero $end
$upscope $end
$scope module inf $end
$var wire 1 % clk $end
$var wire 16 9 mem_addr [15:0] $end
$var reg 32 : ins [31:0] $end
$upscope $end
$scope module op $end
$var wire 1 % clk $end
$var wire 32 ; ins [31:0] $end
$var reg 3 < data_path [2:0] $end
$var reg 3 = type [2:0] $end
$upscope $end
$upscope $end
$upscope $end
$enddefinitions $end
$comment Show the parameter values. $end
$dumpall
$end
#0
$dumpvars
bx =
bx <
bx ;
bx :
b0 9
bx 8
bx 7
bx 6
bx 5
bx 4
b100000 3
bx 2
bx 1
bx 0
bx /
bx .
x-
bx ,
bx +
bx *
bx )
x(
b0 '
b0 &
0%
bx $
bx #
bx "
bx !
$end
#5
b110 ,
b110 <
b1000100000000000100000 +
b1000100000000000100000 :
b1000100000000000100000 ;
1%
#10
0%
#15
0-
b1 !
b1 1
b1 5
b1 "
b1 0
b1 4
b0 )
b0 7
b0 =
b1 ,
b1 <
1%
#20
0%
#25
0(
b10 #
b10 *
b10 8
1%
#30
0%
#35
1%
#40
0%
b1 &
b1 '
b1 9
#45
b1000100000000000100010 +
b1000100000000000100010 :
b1000100000000000100010 ;
1%
#50
0%
#55
b1 )
b1 7
b1 =
1%
#60
0%
b110 &
b110 '
b110 9
#65
b0 #
b0 *
b0 8
b110000001000100000000000100100 +
b110000001000100000000000100100 :
b110000001000100000000000100100 ;
1%
#70
0%
#75
b10 )
b10 7
b10 =
b10 ,
b10 <
1%
#80
0%
b1010 &
b1010 '
b1010 9
#85
b1 #
b1 *
b1 8
b111100001000100000001010000000 +
b111100001000100000001010000000 :
b111100001000100000001010000000 ;
1%
#90
0%
#95
b1010 2
b1010 6
b100 )
b100 7
b100 =
1%
#100
0%
b1110 &
b1110 '
b1110 9
#105
b10000000000 #
b10000000000 *
b10000000000 8
b1010000001000000000000000001010 +
b1010000001000000000000000001010 :
b1010000001000000000000000001010 ;
1%
#110
0%
#115
b111 )
b111 7
b111 =
b110 ,
b110 <
1%
#120
0%
#125
1(
1-
b10000000000 !
b10000000000 1
b10000000000 5
1%
#130
0%
#135
b101000 .
1%
#140
0%
#145
b110110 $
b110110 /
1%
